{
  "chapter": "c18",
  "questions": [
    { "id": "c18_q01", "question": "The central principle of geriatric trauma physiology is:", "options": ["Increased reserve", "Decreased physiologic reserve in every system", "Faster healing", "Resistance to shock"], "correct": 1, "rationale": "Aging reduces reserve everywhere, so older patients tolerate injury poorly and decompensate quickly.", "difficulty": "Easy" },
    { "id": "c18_q02", "question": "A beta-blocker in a bleeding elderly patient may cause:", "options": ["Exaggerated tachycardia", "A blunted heart-rate response that masks shock", "Hypertension", "No effect on assessment"], "correct": 1, "rationale": "Beta-blockers prevent compensatory tachycardia, masking the usual sign of shock.", "difficulty": "Medium" },
    { "id": "c18_q03", "question": "A pacemaker affects shock assessment by:", "options": ["Raising blood pressure", "Fixing the heart rate so tachycardia cannot signal shock", "Causing fever", "Improving perfusion"], "correct": 1, "rationale": "A fixed paced rate removes the tachycardic warning sign of shock.", "difficulty": "Medium" },
    { "id": "c18_q04", "question": "Anticoagulants in an elderly head-injury patient most increase the risk of:", "options": ["Pneumonia", "Intracranial hemorrhage", "Hyperglycemia", "Compartment syndrome"], "correct": 1, "rationale": "Blood thinners dramatically increase intracranial bleeding risk after head trauma.", "difficulty": "Easy" },
    { "id": "c18_q05", "question": "A 'normal' blood pressure in a chronically hypertensive elder may actually represent:", "options": ["Overhydration", "Relative hypotension (shock)", "Excellent perfusion", "Hypertensive crisis"], "correct": 1, "rationale": "Because their baseline is high, a 'normal' reading can be relative hypotension indicating shock.", "difficulty": "Medium" },
    { "id": "c18_q06", "question": "Subdural hematomas develop slowly in the elderly because:", "options": ["Their skulls are thicker", "Brain atrophy stretches bridging veins that tear and bleed slowly", "They never get head injuries", "They have more CSF"], "correct": 1, "rationale": "Atrophy stretches the bridging veins, which bleed slowly, causing delayed symptoms after minor trauma.", "difficulty": "Hard" },
    { "id": "c18_q07", "question": "A kyphotic spine on a backboard should be managed by:", "options": ["Forcing it flat", "Padding the voids for comfortable neutral alignment", "Leaving large gaps", "Applying neck traction"], "correct": 1, "rationale": "Pad the natural curves rather than forcing the spine flat, which can cause injury and pain.", "difficulty": "Medium" },
    { "id": "c18_q08", "question": "Why can a ground-level fall cause major injury in an older adult?", "options": ["They fall harder", "Osteoporosis makes bones fragile (hip, pelvis, ribs)", "They are heavier", "They have stronger bones"], "correct": 1, "rationale": "Fragile osteoporotic bones fracture from low-energy mechanisms like simple falls.", "difficulty": "Easy" },
    { "id": "c18_q09", "question": "Rib fractures in the elderly are dangerous because they:", "options": ["Heal too fast", "Impair ventilation and increase pneumonia risk and mortality", "Have no consequences", "Prevent shock"], "correct": 1, "rationale": "Painful rib fractures limit breathing and markedly raise the risk of pneumonia and death in older patients.", "difficulty": "Medium" },
    { "id": "c18_q10", "question": "Fluid resuscitation in the elderly must be cautious to avoid:", "options": ["Hypoglycemia", "Pulmonary edema and heart failure", "Hypothermia only", "Hypertension"], "correct": 1, "rationale": "Reduced cardiac/renal reserve makes the elderly prone to fluid overload and heart failure.", "difficulty": "Medium" },
    { "id": "c18_q11", "question": "Older patients desaturate faster because of:", "options": ["Increased lung reserve", "Decreased respiratory reserve and lung elasticity", "Larger lungs", "More hemoglobin"], "correct": 1, "rationale": "Reduced respiratory reserve and lung elasticity cause faster desaturation—support breathing early.", "difficulty": "Easy" },
    { "id": "c18_q12", "question": "To interpret a geriatric patient's mental status, you should:", "options": ["Assume any confusion is baseline", "Obtain the patient's baseline from caregivers", "Ignore mental status", "Assume it is always abnormal"], "correct": 1, "rationale": "Knowing the baseline (from caregivers) helps distinguish acute changes from chronic dementia.", "difficulty": "Medium" },
    { "id": "c18_q13", "question": "Why handle elderly patients gently and pad prominences?", "options": ["They prefer it", "Thin skin and fragile bones injure easily", "It speeds transport", "It is optional"], "correct": 1, "rationale": "Fragile skin and bones are easily injured; gentle handling and padding prevent harm.", "difficulty": "Easy" },
    { "id": "c18_q14", "question": "In a geriatric head injury, you should always ask about:", "options": ["Diet", "Anticoagulant/antiplatelet medication use", "Exercise habits", "Family history only"], "correct": 1, "rationale": "Blood thinners greatly increase intracranial bleeding risk and change the urgency of evaluation.", "difficulty": "Easy" },
    { "id": "c18_q15", "question": "The threshold for trauma-center transport in the elderly should be:", "options": ["High—rarely transport", "Low—they benefit from higher-level care even after minor trauma", "Based only on age", "Never"], "correct": 1, "rationale": "Limited reserve and occult-injury risk justify a low threshold for trauma-center transport.", "difficulty": "Medium" },
    { "id": "c18_q16", "question": "Reduced kidney function in the elderly increases the risk of:", "options": ["Better drug clearance", "Fluid overload and altered drug effects", "Hypoglycemia only", "Faster recovery"], "correct": 1, "rationale": "Impaired renal function affects fluid and drug handling, raising overload and toxicity risks.", "difficulty": "Medium" },
    { "id": "c18_q17", "question": "Trusting normal-appearing vital signs in an elderly trauma patient is risky because:", "options": ["Vitals are always accurate", "Medications and baseline hypertension can mask serious injury and shock", "Older patients never have shock", "Vitals do not matter"], "correct": 1, "rationale": "Masked compensation and high baselines mean normal vitals can conceal significant injury.", "difficulty": "Medium" },
    { "id": "c18_q18", "question": "A 78-year-old on warfarin has a minor head bump and a normal exam. The best approach is:", "options": ["Reassure and refuse transport", "Recognize high bleeding risk, monitor closely, and transport for evaluation", "Ignore the mechanism", "Give a fluid bolus"], "correct": 1, "rationale": "Anticoagulation makes even minor head trauma high-risk for delayed intracranial bleeding—transport for evaluation.", "difficulty": "Hard" }
  ]
}
