{"nodes":[{"id":"sw","label":"sw.js","file_type":"code","source_file":"sw.js","source_location":"L1"},{"id":"sw_cache_first_patterns","label":"CACHE_FIRST_PATTERNS","file_type":"code","source_file":"sw.js","source_location":"L30"},{"id":"sw_networkfirst","label":"networkFirst()","file_type":"code","source_file":"sw.js","source_location":"L129"},{"id":"sw_stalewhilerevalidate","label":"staleWhileRevalidate()","file_type":"code","source_file":"sw.js","source_location":"L156"},{"id":"sw_offlinefallback","label":"offlineFallback()","file_type":"code","source_file":"sw.js","source_location":"L199"},{"id":"sw_cachefirst","label":"cacheFirst()","file_type":"code","source_file":"sw.js","source_location":"L236"},{"id":"sw_iscacheable","label":"isCacheable()","file_type":"code","source_file":"sw.js","source_location":"L285"}],"edges":[{"source":"sw","target":"sw_cache_first_patterns","relation":"contains","confidence":"EXTRACTED","source_file":"sw.js","source_location":"L30","weight":1},{"source":"sw","target":"sw_networkfirst","relation":"contains","confidence":"EXTRACTED","source_file":"sw.js","source_location":"L129","weight":1},{"source":"sw","target":"sw_stalewhilerevalidate","relation":"contains","confidence":"EXTRACTED","source_file":"sw.js","source_location":"L156","weight":1},{"source":"sw","target":"sw_offlinefallback","relation":"contains","confidence":"EXTRACTED","source_file":"sw.js","source_location":"L199","weight":1},{"source":"sw","target":"sw_cachefirst","relation":"contains","confidence":"EXTRACTED","source_file":"sw.js","source_location":"L236","weight":1},{"source":"sw","target":"sw_iscacheable","relation":"contains","confidence":"EXTRACTED","source_file":"sw.js","source_location":"L285","weight":1},{"source":"sw_networkfirst","target":"sw_offlinefallback","relation":"calls","confidence":"EXTRACTED","source_file":"sw.js","source_location":"L149","weight":1},{"source":"sw_stalewhilerevalidate","target":"sw_networkfirst","relation":"calls","confidence":"EXTRACTED","source_file":"sw.js","source_location":"L163","weight":1},{"source":"sw_stalewhilerevalidate","target":"sw_offlinefallback","relation":"calls","confidence":"EXTRACTED","source_file":"sw.js","source_location":"L188","weight":1}]}